{
    "avg": {
        "wmc": 11.09,
        "ccn": 6.19,
        "bugs": 0.12,
        "kanDefect": 0.51,
        "relativeSystemComplexity": 122.53,
        "relativeDataComplexity": 1.52,
        "relativeStructuralComplexity": 121.02,
        "volume": 364.74,
        "commentWeight": 23.47,
        "intelligentContent": 38.49,
        "lcom": 1.94,
        "instability": 0.65,
        "afferentCoupling": 2.44,
        "efferentCoupling": 4.64,
        "difficulty": 6.85,
        "mi": 82.95,
        "distance": 0.18,
        "incomingCDep": 3.76,
        "incomingPDep": 2.82,
        "outgoingCDep": 7.7,
        "outgoingPDep": 4.69,
        "classesPerPackage": 2.96
    },
    "sum": {
        "loc": 19923,
        "cloc": 4510,
        "lloc": 15416,
        "nbMethods": 1665,
        "nbClasses": 312,
        "nbInterfaces": 58,
        "nbPackages": 125,
        "violations": {
            "total": 110,
            "information": 14,
            "warning": 66,
            "error": 30,
            "critical": 0
        }
    }
}