{
    "avg": {
        "wmc": 11.6,
        "ccn": 6.6,
        "bugs": 0.13,
        "kanDefect": 0.53,
        "relativeSystemComplexity": 116.79,
        "relativeDataComplexity": 1.55,
        "relativeStructuralComplexity": 115.23,
        "volume": 392.31,
        "commentWeight": 23.3,
        "intelligentContent": 41.21,
        "lcom": 1.95,
        "instability": 0.65,
        "afferentCoupling": 2.36,
        "efferentCoupling": 4.56,
        "difficulty": 6.91,
        "mi": 82.97,
        "distance": 0.18,
        "incomingCDep": 3.57,
        "incomingPDep": 2.62,
        "outgoingCDep": 7.55,
        "outgoingPDep": 4.5,
        "classesPerPackage": 3.05
    },
    "sum": {
        "loc": 17425,
        "cloc": 3810,
        "lloc": 13618,
        "nbMethods": 1442,
        "nbClasses": 267,
        "nbInterfaces": 56,
        "nbPackages": 106,
        "violations": {
            "total": 107,
            "information": 14,
            "warning": 65,
            "error": 28,
            "critical": 0
        }
    }
}