{
    "avg": {
        "wmc": 11.35,
        "ccn": 6.44,
        "bugs": 0.13,
        "kanDefect": 0.52,
        "relativeSystemComplexity": 120.65,
        "relativeDataComplexity": 1.51,
        "relativeStructuralComplexity": 119.14,
        "volume": 381.35,
        "commentWeight": 22.73,
        "intelligentContent": 40.22,
        "lcom": 1.96,
        "instability": 0.65,
        "afferentCoupling": 2.44,
        "efferentCoupling": 4.61,
        "difficulty": 6.82,
        "mi": 82.21,
        "distance": 0.18,
        "incomingCDep": 3.76,
        "incomingPDep": 2.81,
        "outgoingCDep": 7.55,
        "outgoingPDep": 4.6,
        "classesPerPackage": 2.94
    },
    "sum": {
        "loc": 18760,
        "cloc": 4035,
        "lloc": 14728,
        "nbMethods": 1566,
        "nbClasses": 294,
        "nbInterfaces": 56,
        "nbPackages": 119,
        "violations": {
            "total": 111,
            "information": 15,
            "warning": 67,
            "error": 29,
            "critical": 0
        }
    }
}